{
  "jobId": "job_NkwFxeHARqc_1762214229467",
  "videoId": "NkwFxeHARqc",
  "url": "https://youtu.be/NkwFxeHARqc",
  "status": "done",
  "progress": 100,
  "stages": {
    "input": {
      "status": "done",
      "progress": 100
    },
    "transcribe": {
      "status": "done",
      "progress": 100
    },
    "fastSummary": {
      "status": "done",
      "progress": 100
    },
    "indexing": {
      "status": "done",
      "progress": 100
    },
    "llmReady": {
      "status": "done",
      "progress": 100
    }
  },
  "startedAt": "2025-11-03T23:57:09.467Z",
  "updatedAt": "2025-11-03T23:59:18.200Z",
  "completedAt": "2025-11-03T23:59:18.200Z"
}
